csv_to_anki_converter/__init__.py
csv_to_anki_converter/cli.py
csv_to_anki_converter/converter.py
csv_to_anki_converter/models.py
csv_to_anki_converter-1.2.0.dist-info/licenses/LICENSE
csv_to_anki_converter-1.2.0.dist-info/METADATA
csv_to_anki_converter-1.2.0.dist-info/WHEEL
csv_to_anki_converter-1.2.0.dist-info/entry_points.txt
csv_to_anki_converter-1.2.0.dist-info/top_level.txt
csv_to_anki_converter-1.2.0.dist-info/RECORD
