Metadata-Version: 2.4
Name: csv-to-anki-converter
Version: 1.2.0
Summary: Convert CSV files to Anki deck packages with ease
Home-page: https://github.com/NurNichtWilly/ankipak
Author: Willy
Author-email: Willy <willy@example.com>
Maintainer-email: Willy <willy@example.com>
License: MIT
Project-URL: Homepage, https://github.com/NurNichtWilly/ankipak
Project-URL: Documentation, https://github.com/NurNichtWilly/ankipak#readme
Project-URL: Repository, https://github.com/NurNichtWilly/ankipak
Project-URL: Bug Tracker, https://github.com/NurNichtWilly/ankipak/issues
Project-URL: Changelog, https://github.com/NurNichtWilly/ankipak/blob/main/CHANGELOG.md
Keywords: anki,flashcards,csv,converter,education,study
Classifier: Development Status :: 5 - Production/Stable
Classifier: Intended Audience :: Education
Classifier: Intended Audience :: End Users/Desktop
Classifier: Topic :: Education
Classifier: Topic :: Utilities
Classifier: License :: OSI Approved :: MIT License
Classifier: Programming Language :: Python :: 3
Classifier: Programming Language :: Python :: 3.8
Classifier: Programming Language :: Python :: 3.9
Classifier: Programming Language :: Python :: 3.10
Classifier: Programming Language :: Python :: 3.11
Classifier: Programming Language :: Python :: 3.12
Classifier: Operating System :: OS Independent
Requires-Python: >=3.8
License-File: LICENSE
Requires-Dist: pandas>=1.3.0
Requires-Dist: genanki>=0.13.0
Provides-Extra: dev
Requires-Dist: pytest>=6.0; extra == "dev"
Requires-Dist: pytest-cov>=2.0; extra == "dev"
Requires-Dist: black>=21.0; extra == "dev"
Requires-Dist: flake8>=3.8; extra == "dev"
Requires-Dist: mypy>=0.800; extra == "dev"
Requires-Dist: build>=0.8.0; extra == "dev"
Requires-Dist: twine>=4.0.0; extra == "dev"
Dynamic: author
Dynamic: home-page
Dynamic: license-file
Dynamic: requires-python
